meoww/__init__.py
meoww/__main__.py
meoww/cat.py
meoww/cursor.py
meoww/game.py
meoww/settings.py
meoww/util.py
meoww/window.py
meoww/assets/images/background.png
meoww/assets/images/cat.png
meoww/assets/images/cursor.png
meoww/assets/images/icon.jpg
meoww-0.1.0.dist-info/LICENSE
meoww-0.1.0.dist-info/METADATA
meoww-0.1.0.dist-info/WHEEL
meoww-0.1.0.dist-info/entry_points.txt
meoww-0.1.0.dist-info/top_level.txt
meoww-0.1.0.dist-info/RECORD
