Metadata-Version: 2.1
Name: meoww
Version: 0.1.0
Summary: Meoww meoww meoww
Home-page: https://github.com/png261/meoww
Download-URL: https://github.com/png261/meoww/archive/0.1.0.tar.gz
Author: Phuong Nguyen
Author-email: nhphuong.code@gmail.com
License: MIT
Keywords: meoww
Classifier: Environment :: X11 Applications
Classifier: License :: OSI Approved :: MIT License
Classifier: Operating System :: POSIX :: Linux
Classifier: Programming Language :: Python :: 3.5
Classifier: Programming Language :: Python :: 3.6
Requires-Python: >=3.5
License-File: LICENSE
Requires-Dist: pygame (>=2.4.0)
